.hgignore
.hgtags
README.txt
setup.py
Cuttlefish.egg-info/PKG-INFO
Cuttlefish.egg-info/SOURCES.txt
Cuttlefish.egg-info/dependency_links.txt
Cuttlefish.egg-info/entry_points.txt
Cuttlefish.egg-info/not-zip-safe
Cuttlefish.egg-info/requires.txt
Cuttlefish.egg-info/top_level.txt
cuttlefish/__init__.py
cuttlefish/cuttlefish-config.plist
cuttlefish/cuttlefish.wsgi
cuttlefish/static/LICENSE.txt
cuttlefish/static/bottle-sig.png
cuttlefish/static/cuttlefish.png
cuttlefish/static/mako-sig.png
cuttlefish/static/style.css